LICENSE.txt
README.md
setup.cfg
setup.py
Topsis_KaramveerSingh_102003139/__init__.py
Topsis_KaramveerSingh_102003139/topsis_102003139.py
Topsis_KaramveerSingh_102003139.egg-info/PKG-INFO
Topsis_KaramveerSingh_102003139.egg-info/SOURCES.txt
Topsis_KaramveerSingh_102003139.egg-info/dependency_links.txt
Topsis_KaramveerSingh_102003139.egg-info/requires.txt
Topsis_KaramveerSingh_102003139.egg-info/top_level.txt