Metadata-Version: 2.1
Name: Topsis-KaramveerSingh-102003139
Version: 0.1
Summary: This package is implimentation of multi-criteria decision analysis using topsis
Home-page: https://github.com/kzaildar26/Topsis_KaramveerSingh_102003139
Download-URL: https://github.com/kzaildar26/Topsis_KaramveerSingh_102003139/archive/refs/tags/ver_0.1.tar.gz
Author: Karamveer Singh
Author-email: ksingh_be20@thapar.edu
License: MIT
Keywords: topsis
Classifier: Development Status :: 3 - Alpha
Classifier: Intended Audience :: Developers
Classifier: Topic :: Software Development :: Build Tools
Classifier: License :: OSI Approved :: MIT License
Classifier: Programming Language :: Python :: 3
Classifier: Programming Language :: Python :: 3.4
Classifier: Programming Language :: Python :: 3.5
Classifier: Programming Language :: Python :: 3.6
License-File: LICENSE.txt
